focsec/__init__.py
focsec/cli.py
focsec/client.py
focsec/exceptions.py
focsec/models.py
focsec-1.0.0.dist-info/licenses/LICENSE
focsec-1.0.0.dist-info/METADATA
focsec-1.0.0.dist-info/WHEEL
focsec-1.0.0.dist-info/entry_points.txt
focsec-1.0.0.dist-info/top_level.txt
focsec-1.0.0.dist-info/RECORD
